tdastro/__init__.py
tdastro/_version.py
tdastro/base_models.py
tdastro/consts.py
tdastro/graph_state.py
tdastro/simulate.py
tdastro/astro_utils/__init__.py
tdastro/astro_utils/agn_utils.py
tdastro/astro_utils/black_body.py
tdastro/astro_utils/dustmap.py
tdastro/astro_utils/mag_flux.py
tdastro/astro_utils/noise_model.py
tdastro/astro_utils/obs_utils.py
tdastro/astro_utils/passbands.py
tdastro/astro_utils/pzflow_node.py
tdastro/astro_utils/redshift.py
tdastro/astro_utils/salt2_color_law.py
tdastro/astro_utils/snia_utils.py
tdastro/astro_utils/unit_utils.py
tdastro/astro_utils/zeropoint.py
tdastro/effects/__init__.py
tdastro/effects/basic_effects.py
tdastro/effects/effect_model.py
tdastro/effects/extinction.py
tdastro/effects/microlensing.py
tdastro/effects/white_noise.py
tdastro/example_runs/simulate_snia.py
tdastro/math_nodes/__init__.py
tdastro/math_nodes/basic_math_node.py
tdastro/math_nodes/distribution_sampler.py
tdastro/math_nodes/given_sampler.py
tdastro/math_nodes/np_random.py
tdastro/math_nodes/ra_dec_sampler.py
tdastro/math_nodes/scipy_random.py
tdastro/math_nodes/single_value_node.py
tdastro/models/__init__.py
tdastro/models/agn.py
tdastro/models/basic_models.py
tdastro/models/bayesn.py
tdastro/models/galaxy_models.py
tdastro/models/lightcurve_template_model.py
tdastro/models/multi_object_model.py
tdastro/models/periodic_model.py
tdastro/models/periodic_variable_star.py
tdastro/models/physical_model.py
tdastro/models/salt2_jax.py
tdastro/models/sncomso_models.py
tdastro/models/snia_host.py
tdastro/models/spline_model.py
tdastro/models/static_sed_model.py
tdastro/obstable/__init__.py
tdastro/obstable/obs_table.py
tdastro/obstable/opsim.py
tdastro/obstable/ztf_obstable.py
tdastro/utils/__init__.py
tdastro/utils/bicubic_interp.py
tdastro/utils/data_download.py
tdastro/utils/io_utils.py
tdastro/utils/plotting.py
tdastro/utils/wave_extrapolate.py
tdastro-0.0.7.dist-info/licenses/LICENSE
tdastro-0.0.7.dist-info/METADATA
tdastro-0.0.7.dist-info/WHEEL
tdastro-0.0.7.dist-info/top_level.txt
tdastro-0.0.7.dist-info/RECORD
