Metadata-Version: 2.4
Name: tdastro
Version: 0.0.7
Author-email: LINCC Frameworks <lincc-frameworks-team@lists.lsst.org>
License: MIT License
Project-URL: Source Code, https://github.com/lincc-frameworks/tdastro
Classifier: Development Status :: 4 - Beta
Classifier: License :: OSI Approved :: MIT License
Classifier: Intended Audience :: Developers
Classifier: Intended Audience :: Science/Research
Classifier: Operating System :: OS Independent
Classifier: Programming Language :: Python
Requires-Python: >=3.10
License-File: LICENSE
Requires-Dist: astropy
Requires-Dist: cdshealpix
Requires-Dist: citation-compass>=0.0.3
Requires-Dist: dust_extinction
Requires-Dist: extinction>=0.4.7
Requires-Dist: jax
Requires-Dist: matplotlib
Requires-Dist: mocpy
Requires-Dist: nested-pandas
Requires-Dist: numpy>2.0
Requires-Dist: pandas
Requires-Dist: pooch
Requires-Dist: scipy
Provides-Extra: dev
Requires-Dist: asv==0.6.4; extra == "dev"
Requires-Dist: fsspec[http]; extra == "dev"
Requires-Dist: jupyter; extra == "dev"
Requires-Dist: pre-commit; extra == "dev"
Requires-Dist: pytest; extra == "dev"
Requires-Dist: pytest-cov; extra == "dev"
Requires-Dist: pzflow; extra == "dev"
Requires-Dist: ruff; extra == "dev"
Requires-Dist: sncosmo; extra == "dev"
Requires-Dist: synphot; extra == "dev"
Requires-Dist: VBMicrolensing; extra == "dev"
Provides-Extra: all
Requires-Dist: pzflow; extra == "all"
Requires-Dist: sncosmo; extra == "all"
Requires-Dist: synphot; extra == "all"
Requires-Dist: VBMicrolensing; extra == "all"
Dynamic: license-file
